ronchang/__init__.py
ronchang/bar.py
ronchang/parser.py
ronchang/slicer.py
ronchang/snaptimer.py
ronchang/timer.py
snaptimer/__init__.py
snaptimer/snaptimer.py
ronchang-0.1.3.dist-info/LICENSE
ronchang-0.1.3.dist-info/METADATA
ronchang-0.1.3.dist-info/WHEEL
ronchang-0.1.3.dist-info/top_level.txt
ronchang-0.1.3.dist-info/RECORD
