Metadata-Version: 2.1
Name: ronchang
Version: 0.1.3
Summary: Hands on toolkits
Home-page: https://github.com/Ron-Chang/ronchang
Author: Ron Chang
Author-email: ron.hsien.chang@gmail.com
License: MIT
Platform: UNKNOWN
Requires-Python: >=3.6
Requires-Dist: colorama (==0.4.3)
